{
  "exercises": [
    {
      "id": "_05pbj5ob",
      "createdAt": "2019-11-11T21:23:48.684Z",
      "name": "Elliptical, Warmup",
      "category": "Cardio",
      "desc": "",
      "inputs": {
        "hasNotes": true,
        "hasDuration": true,
        "hasDistance": true,
        "hasWeight": false,
        "hasReps": false
      },
      "objectives": [
        { "type": "Notes", "text": "Notes" },
        { "type": "Intensity", "text": "Medium" },
        { "type": "Resistence", "text": "8/20" },
        { "type": "Incline", "text": "0/20" }
      ],
      "records": [
        {
          "createdAt": "2019-11-11T21:23:48.684Z",
          "sets": [
            {
              "duration": 420,
              "distance": { "miles": 0.5, "kilometers": 0.8 },
              "weight": null,
              "reps": null
            }
          ]
        }
      ]
    },
    {
      "id": "_kplyey7i",
      "createdAt": "2019-11-11T21:23:48.685Z",
      "name": "Elliptical, Intervals",
      "desc": "",
      "inputs": {
        "hasNotes": true,
        "hasDuration": true,
        "hasDistance": true,
        "hasWeight": false,
        "hasReps": false
      },
      "objectives": [
        { "type": "Notes", "text": "Notes" },
        { "type": "Intensity", "text": "High" },
        { "type": "Resistence", "text": "8/20" },
        { "type": "Incline", "text": "0/20" }
      ],
      "records": [
        {
          "createdAt": "2019-11-11T21:23:48.685Z",
          "sets": [
            {
              "duration": 1440,
              "distance": { "miles": 2, "kilometers": 3.22 },
              "weight": null,
              "reps": null
            }
          ]
        }
      ]
    },
    {
      "id": "_dxs8ojvr",
      "createdAt": "2019-11-11T21:23:48.685Z",
      "name": "Stretching",
      "category": "Miscellaneous",
      "desc": "",
      "inputs": {
        "hasNotes": true,
        "hasDuration": true,
        "hasDistance": false,
        "hasWeight": false,
        "hasReps": false
      },
      "objectives": [
        { "type": "Notes", "text": "Notes" },
        { "type": "Intensity", "text": "Medium" }
      ],
      "records": [
        {
          "createdAt": "2019-11-11T21:23:48.685Z",
          "sets": [
            { "duration": 540, "distance": null, "weight": null, "reps": null }
          ]
        }
      ]
    },
    {
      "id": "_magkmc34",
      "createdAt": "2019-11-11T21:23:48.685Z",
      "name": "Flat Bench Press",
      "category": "Chest",
      "desc": "",
      "inputs": {
        "hasNotes": true,
        "hasDuration": false,
        "hasDistance": false,
        "hasWeight": true,
        "hasReps": true
      },
      "objectives": [
        { "type": "Notes", "text": "Notes" },
        { "type": "Breaks", "text": "2m" },
        { "type": "Tempo", "text": "Normal" },
        { "type": "Intensity", "text": "High" }
      ],
      "records": [
        {
          "createdAt": "2019-11-11T21:23:48.685Z",
          "sets": [
            {
              "duration": null,
              "distance": null,
              "weight": { "pounds": 130, "kilograms": 58.97 },
              "reps": 10
            },
            {
              "duration": null,
              "distance": null,
              "weight": { "pounds": 130, "kilograms": 58.97 },
              "reps": 10
            },
            {
              "duration": null,
              "distance": null,
              "weight": { "pounds": 130, "kilograms": 58.97 },
              "reps": 10
            },
            {
              "duration": null,
              "distance": null,
              "weight": { "pounds": 130, "kilograms": 58.97 },
              "reps": 10
            }
          ]
        }
      ]
    },
    {
      "id": "_sk0hdyyh",
      "createdAt": "2019-11-11T21:23:48.685Z",
      "name": "Incline Bench Press",
      "category": "Chest",
      "desc": "",
      "inputs": {
        "hasNotes": true,
        "hasDuration": false,
        "hasDistance": false,
        "hasWeight": true,
        "hasReps": true
      },
      "objectives": [
        { "type": "Notes", "text": "Notes" },
        { "type": "Breaks", "text": "2m" },
        { "type": "Tempo", "text": "Normal" },
        { "type": "Intensity", "text": "High" }
      ],
      "records": [
        {
          "createdAt": "2019-11-11T21:23:48.685Z",
          "sets": [
            {
              "duration": null,
              "distance": null,
              "weight": { "pounds": 75, "kilograms": 34.02 },
              "reps": 10
            },
            {
              "duration": null,
              "distance": null,
              "weight": { "pounds": 75, "kilograms": 34.02 },
              "reps": 10
            },
            {
              "duration": null,
              "distance": null,
              "weight": { "pounds": 75, "kilograms": 34.02 },
              "reps": 10
            },
            {
              "duration": null,
              "distance": null,
              "weight": { "pounds": 75, "kilograms": 34.02 },
              "reps": 10
            }
          ]
        }
      ]
    },
    {
      "id": "_20w6dhq8",
      "createdAt": "2019-11-11T21:23:48.685Z",
      "name": "Decline Bench Press",
      "category": "Chest",
      "desc": "",
      "inputs": {
        "hasNotes": true,
        "hasDuration": false,
        "hasDistance": false,
        "hasWeight": true,
        "hasReps": true
      },
      "objectives": [
        { "type": "Notes", "text": "Notes" },
        { "type": "Breaks", "text": "2m" },
        { "type": "Tempo", "text": "Normal" },
        { "type": "Intensity", "text": "High" }
      ],
      "records": [
        {
          "createdAt": "2019-11-11T21:23:48.685Z",
          "sets": [
            {
              "duration": null,
              "distance": null,
              "weight": { "pounds": 130, "kilograms": 58.97 },
              "reps": 10
            },
            {
              "duration": null,
              "distance": null,
              "weight": { "pounds": 130, "kilograms": 58.97 },
              "reps": 10
            },
            {
              "duration": null,
              "distance": null,
              "weight": { "pounds": 130, "kilograms": 58.97 },
              "reps": 10
            },
            {
              "duration": null,
              "distance": null,
              "weight": { "pounds": 130, "kilograms": 58.97 },
              "reps": 10
            }
          ]
        }
      ]
    },
    {
      "id": "_wbimtk4s",
      "createdAt": "2019-11-11T21:23:48.685Z",
      "name": "Fly Machine (Chest)",
      "category": "Chest",
      "desc": "",
      "inputs": {
        "hasNotes": true,
        "hasDuration": false,
        "hasDistance": false,
        "hasWeight": true,
        "hasReps": true
      },
      "objectives": [
        { "type": "Notes", "text": "Notes" },
        { "type": "Breaks", "text": "2m" },
        { "type": "Tempo", "text": "Slow" },
        { "type": "Intensity", "text": "High" }
      ],
      "records": [
        {
          "createdAt": "2019-11-11T21:23:48.685Z",
          "sets": [
            {
              "duration": null,
              "distance": null,
              "weight": { "pounds": 120, "kilograms": 54.43 },
              "reps": 10
            },
            {
              "duration": null,
              "distance": null,
              "weight": { "pounds": 120, "kilograms": 54.43 },
              "reps": 10
            },
            {
              "duration": null,
              "distance": null,
              "weight": { "pounds": 120, "kilograms": 54.43 },
              "reps": 10
            }
          ]
        }
      ]
    },
    {
      "id": "_7l0vnu8k",
      "createdAt": "2019-11-11T21:23:48.685Z",
      "name": "Cable Tricep Pulldowns",
      "category": "Triceps",
      "desc": "",
      "inputs": {
        "hasNotes": true,
        "hasDuration": false,
        "hasDistance": false,
        "hasWeight": true,
        "hasReps": true
      },
      "objectives": [
        { "type": "Notes", "text": "Notes" },
        { "type": "Breaks", "text": "1m 30s" },
        { "type": "Tempo", "text": "Normal" },
        { "type": "Intensity", "text": "High" }
      ],
      "records": [
        {
          "createdAt": "2019-11-11T21:23:48.685Z",
          "sets": [
            {
              "duration": null,
              "distance": null,
              "weight": { "pounds": 42.5, "kilograms": 19.28 },
              "reps": 10
            },
            {
              "duration": null,
              "distance": null,
              "weight": { "pounds": 42.5, "kilograms": 19.28 },
              "reps": 10
            },
            {
              "duration": null,
              "distance": null,
              "weight": { "pounds": 42.5, "kilograms": 19.28 },
              "reps": 10
            }
          ]
        }
      ]
    },
    {
      "id": "_t6a1ipsj",
      "createdAt": "2019-11-11T21:23:48.685Z",
      "name": "Tricep Press Machine",
      "category": "Triceps",
      "desc": "",
      "inputs": {
        "hasNotes": true,
        "hasDuration": false,
        "hasDistance": false,
        "hasWeight": true,
        "hasReps": true
      },
      "objectives": [
        { "type": "Notes", "text": "Notes" },
        { "type": "Breaks", "text": "1m 30s" },
        { "type": "Tempo", "text": "Normal" },
        { "type": "Intensity", "text": "High" }
      ],
      "records": [
        {
          "createdAt": "2019-11-11T21:23:48.685Z",
          "sets": [
            {
              "duration": null,
              "distance": null,
              "weight": { "pounds": 190, "kilograms": 86.18 },
              "reps": 10
            },
            {
              "duration": null,
              "distance": null,
              "weight": { "pounds": 190, "kilograms": 86.18 },
              "reps": 10
            },
            {
              "duration": null,
              "distance": null,
              "weight": { "pounds": 190, "kilograms": 86.18 },
              "reps": 10
            }
          ]
        }
      ]
    },
    {
      "id": "_p9nuiehd",
      "createdAt": "2019-11-11T21:23:48.685Z",
      "name": "Bent Over Rows",
      "category": "Back",
      "desc": "",
      "inputs": {
        "hasNotes": true,
        "hasDuration": false,
        "hasDistance": false,
        "hasWeight": true,
        "hasReps": true
      },
      "objectives": [
        { "type": "Notes", "text": "Notes" },
        { "type": "Breaks", "text": "2m" },
        { "type": "Tempo", "text": "Normal" },
        { "type": "Intensity", "text": "High" }
      ],
      "records": [
        {
          "createdAt": "2019-11-11T21:23:48.685Z",
          "sets": [
            {
              "duration": null,
              "distance": null,
              "weight": { "pounds": 120, "kilograms": 54.43 },
              "reps": 10
            },
            {
              "duration": null,
              "distance": null,
              "weight": { "pounds": 120, "kilograms": 54.43 },
              "reps": 10
            },
            {
              "duration": null,
              "distance": null,
              "weight": { "pounds": 120, "kilograms": 54.43 },
              "reps": 10
            },
            {
              "duration": null,
              "distance": null,
              "weight": { "pounds": 120, "kilograms": 54.43 },
              "reps": 10
            }
          ]
        }
      ]
    },
    {
      "id": "_kkrk4umz",
      "createdAt": "2019-11-11T21:23:48.685Z",
      "name": "Shrugs",
      "category": "Back",
      "desc": "",
      "inputs": {
        "hasNotes": true,
        "hasDuration": false,
        "hasDistance": false,
        "hasWeight": true,
        "hasReps": true
      },
      "objectives": [
        { "type": "Notes", "text": "Notes" },
        { "type": "Breaks", "text": "2m" },
        { "type": "Tempo", "text": "Normal" },
        { "type": "Intensity", "text": "High" }
      ],
      "records": [
        {
          "createdAt": "2019-11-11T21:23:48.685Z",
          "sets": [
            {
              "duration": null,
              "distance": null,
              "weight": { "pounds": 190, "kilograms": 86.18 },
              "reps": 10
            },
            {
              "duration": null,
              "distance": null,
              "weight": { "pounds": 190, "kilograms": 86.18 },
              "reps": 10
            },
            {
              "duration": null,
              "distance": null,
              "weight": { "pounds": 190, "kilograms": 86.18 },
              "reps": 10
            },
            {
              "duration": null,
              "distance": null,
              "weight": { "pounds": 190, "kilograms": 86.18 },
              "reps": 10
            }
          ]
        }
      ]
    },
    {
      "id": "_1bkqyihd",
      "createdAt": "2019-11-11T21:23:48.685Z",
      "name": "Stiff-Leg Deadlifts",
      "category": "Back",
      "desc": "",
      "inputs": {
        "hasNotes": true,
        "hasDuration": false,
        "hasDistance": false,
        "hasWeight": true,
        "hasReps": true
      },
      "objectives": [
        { "type": "Notes", "text": "Notes" },
        { "type": "Breaks", "text": "2m" },
        { "type": "Tempo", "text": "Normal" },
        { "type": "Intensity", "text": "High" }
      ],
      "records": [
        {
          "createdAt": "2019-11-11T21:23:48.685Z",
          "sets": [
            {
              "duration": null,
              "distance": null,
              "weight": { "pounds": 120, "kilograms": 54.43 },
              "reps": 10
            },
            {
              "duration": null,
              "distance": null,
              "weight": { "pounds": 120, "kilograms": 54.43 },
              "reps": 10
            },
            {
              "duration": null,
              "distance": null,
              "weight": { "pounds": 120, "kilograms": 54.43 },
              "reps": 10
            },
            {
              "duration": null,
              "distance": null,
              "weight": { "pounds": 120, "kilograms": 54.43 },
              "reps": 10
            }
          ]
        }
      ]
    },
    {
      "id": "_nidp54eh",
      "createdAt": "2019-11-11T21:23:48.685Z",
      "name": "Assisted Pull-ups",
      "category": "Back",
      "desc": "",
      "inputs": {
        "hasNotes": true,
        "hasDuration": false,
        "hasDistance": false,
        "hasWeight": true,
        "hasReps": true
      },
      "objectives": [
        { "type": "Notes", "text": "Notes" },
        { "type": "Breaks", "text": "2m" },
        { "type": "Tempo", "text": "Normal" },
        { "type": "Intensity", "text": "High" }
      ],
      "records": [
        {
          "createdAt": "2019-11-11T21:23:48.685Z",
          "sets": [
            {
              "duration": null,
              "distance": null,
              "weight": { "pounds": -25, "kilograms": -11.34 },
              "reps": 10
            },
            {
              "duration": null,
              "distance": null,
              "weight": { "pounds": -25, "kilograms": -11.34 },
              "reps": 10
            },
            {
              "duration": null,
              "distance": null,
              "weight": { "pounds": -25, "kilograms": -11.34 },
              "reps": 10
            }
          ]
        }
      ]
    },
    {
      "id": "_0ogbtvmk",
      "createdAt": "2019-11-11T21:23:48.685Z",
      "name": "Overhand Curls",
      "category": "Biceps",
      "desc": "",
      "inputs": {
        "hasNotes": true,
        "hasDuration": false,
        "hasDistance": false,
        "hasWeight": true,
        "hasReps": true
      },
      "objectives": [
        { "type": "Notes", "text": "Notes" },
        { "type": "Breaks", "text": "2m" },
        { "type": "Tempo", "text": "Normal" },
        { "type": "Intensity", "text": "Medium" }
      ],
      "records": [
        {
          "createdAt": "2019-11-11T21:23:48.685Z",
          "sets": [
            {
              "duration": null,
              "distance": null,
              "weight": { "pounds": 15, "kilograms": 6.8 },
              "reps": 10
            },
            {
              "duration": null,
              "distance": null,
              "weight": { "pounds": 15, "kilograms": 6.8 },
              "reps": 10
            },
            {
              "duration": null,
              "distance": null,
              "weight": { "pounds": 15, "kilograms": 6.8 },
              "reps": 10
            }
          ]
        }
      ]
    },
    {
      "id": "_749c818z",
      "createdAt": "2019-11-11T21:23:48.685Z",
      "name": "Underhand Curls",
      "category": "Biceps",
      "desc": "",
      "inputs": {
        "hasNotes": true,
        "hasDuration": false,
        "hasDistance": false,
        "hasWeight": true,
        "hasReps": true
      },
      "objectives": [
        { "type": "Notes", "text": "Notes" },
        { "type": "Breaks", "text": "2m" },
        { "type": "Tempo", "text": "Normal" },
        { "type": "Intensity", "text": "High" }
      ],
      "records": [
        {
          "createdAt": "2019-11-11T21:23:48.685Z",
          "sets": [
            {
              "duration": null,
              "distance": null,
              "weight": { "pounds": 30, "kilograms": 13.61 },
              "reps": 10
            },
            {
              "duration": null,
              "distance": null,
              "weight": { "pounds": 30, "kilograms": 13.61 },
              "reps": 10
            },
            {
              "duration": null,
              "distance": null,
              "weight": { "pounds": 30, "kilograms": 13.61 },
              "reps": 10
            }
          ]
        }
      ]
    },
    {
      "id": "_9gp3tgrp",
      "createdAt": "2019-11-11T21:23:48.685Z",
      "name": "Hammer Curls",
      "category": "Biceps",
      "desc": "",
      "inputs": {
        "hasNotes": true,
        "hasDuration": false,
        "hasDistance": false,
        "hasWeight": true,
        "hasReps": true
      },
      "objectives": [
        { "type": "Notes", "text": "Notes" },
        { "type": "Breaks", "text": "2m" },
        { "type": "Tempo", "text": "Normal" },
        { "type": "Intensity", "text": "High" }
      ],
      "records": [
        {
          "createdAt": "2019-11-11T21:23:48.685Z",
          "sets": [
            {
              "duration": null,
              "distance": null,
              "weight": { "pounds": 30, "kilograms": 13.61 },
              "reps": 10
            },
            {
              "duration": null,
              "distance": null,
              "weight": { "pounds": 30, "kilograms": 13.61 },
              "reps": 10
            },
            {
              "duration": null,
              "distance": null,
              "weight": { "pounds": 30, "kilograms": 13.61 },
              "reps": 10
            }
          ]
        }
      ]
    },
    {
      "id": "_v4xefkci",
      "createdAt": "2019-11-11T21:23:48.685Z",
      "name": "Side Raises",
      "category": "Shoudlers",
      "desc": "",
      "inputs": {
        "hasNotes": true,
        "hasDuration": false,
        "hasDistance": false,
        "hasWeight": true,
        "hasReps": true
      },
      "objectives": [
        { "type": "Notes", "text": "Notes" },
        { "type": "Breaks", "text": "1m" },
        { "type": "Tempo", "text": "Normal" },
        { "type": "Intensity", "text": "High" }
      ],
      "records": [
        {
          "createdAt": "2019-11-11T21:23:48.685Z",
          "sets": [
            {
              "duration": null,
              "distance": null,
              "weight": { "pounds": 10, "kilograms": 4.54 },
              "reps": 10
            },
            {
              "duration": null,
              "distance": null,
              "weight": { "pounds": 10, "kilograms": 4.54 },
              "reps": 10
            },
            {
              "duration": null,
              "distance": null,
              "weight": { "pounds": 10, "kilograms": 4.54 },
              "reps": 10
            }
          ]
        }
      ]
    },
    {
      "id": "_o2r0jlth",
      "createdAt": "2019-11-11T21:23:48.685Z",
      "name": "Front Raises",
      "category": "Shoudlers",
      "desc": "",
      "inputs": {
        "hasNotes": true,
        "hasDuration": false,
        "hasDistance": false,
        "hasWeight": true,
        "hasReps": true
      },
      "objectives": [
        { "type": "Notes", "text": "Notes" },
        { "type": "Breaks", "text": "1m" },
        { "type": "Tempo", "text": "Normal" },
        { "type": "Intensity", "text": "High" }
      ],
      "records": [
        {
          "createdAt": "2019-11-11T21:23:48.685Z",
          "sets": [
            {
              "duration": null,
              "distance": null,
              "weight": { "pounds": 10, "kilograms": 4.54 },
              "reps": 10
            },
            {
              "duration": null,
              "distance": null,
              "weight": { "pounds": 10, "kilograms": 4.54 },
              "reps": 10
            },
            {
              "duration": null,
              "distance": null,
              "weight": { "pounds": 10, "kilograms": 4.54 },
              "reps": 10
            }
          ]
        }
      ]
    },
    {
      "id": "_i9vgny5c",
      "createdAt": "2019-11-11T21:23:48.685Z",
      "name": "Shoulder Press Machine",
      "category": "Shoudlers",
      "desc": "",
      "inputs": {
        "hasNotes": true,
        "hasDuration": false,
        "hasDistance": false,
        "hasWeight": true,
        "hasReps": true
      },
      "objectives": [
        { "type": "Notes", "text": "Notes" },
        { "type": "Breaks", "text": "2m" },
        { "type": "Tempo", "text": "Normal" },
        { "type": "Intensity", "text": "High" }
      ],
      "records": [
        {
          "createdAt": "2019-11-11T21:23:48.685Z",
          "sets": [
            {
              "duration": null,
              "distance": null,
              "weight": { "pounds": 60, "kilograms": 27.22 },
              "reps": 10
            },
            {
              "duration": null,
              "distance": null,
              "weight": { "pounds": 60, "kilograms": 27.22 },
              "reps": 10
            },
            {
              "duration": null,
              "distance": null,
              "weight": { "pounds": 60, "kilograms": 27.22 },
              "reps": 10
            }
          ]
        }
      ]
    },
    {
      "id": "_soelhkyp",
      "createdAt": "2019-11-11T21:23:48.685Z",
      "name": "Leg Press Machine",
      "category": "Legs",
      "desc": "",
      "inputs": {
        "hasNotes": true,
        "hasDuration": false,
        "hasDistance": false,
        "hasWeight": true,
        "hasReps": true
      },
      "objectives": [
        { "type": "Notes", "text": "Notes" },
        { "type": "Breaks", "text": "1m" },
        { "type": "Tempo", "text": "Normal" },
        { "type": "Intensity", "text": "Medium" }
      ],
      "records": [
        {
          "createdAt": "2019-11-11T21:23:48.685Z",
          "sets": [
            {
              "duration": null,
              "distance": null,
              "weight": { "pounds": 175, "kilograms": 79.38 },
              "reps": 10
            },
            {
              "duration": null,
              "distance": null,
              "weight": { "pounds": 175, "kilograms": 79.38 },
              "reps": 10
            },
            {
              "duration": null,
              "distance": null,
              "weight": { "pounds": 175, "kilograms": 79.38 },
              "reps": 10
            }
          ]
        }
      ]
    },
    {
      "id": "_h0ttfb8p",
      "createdAt": "2019-11-11T21:23:48.685Z",
      "name": "Leg Extension Machine",
      "category": "Legs",
      "desc": "",
      "inputs": {
        "hasNotes": true,
        "hasDuration": false,
        "hasDistance": false,
        "hasWeight": true,
        "hasReps": true
      },
      "objectives": [
        { "type": "Notes", "text": "Notes" },
        { "type": "Breaks", "text": "1m" },
        { "type": "Tempo", "text": "Normal" },
        { "type": "Intensity", "text": "Medium" }
      ],
      "records": [
        {
          "createdAt": "2019-11-11T21:23:48.685Z",
          "sets": [
            {
              "duration": null,
              "distance": null,
              "weight": { "pounds": 90, "kilograms": 40.82 },
              "reps": 10
            },
            {
              "duration": null,
              "distance": null,
              "weight": { "pounds": 90, "kilograms": 40.82 },
              "reps": 10
            },
            {
              "duration": null,
              "distance": null,
              "weight": { "pounds": 90, "kilograms": 40.82 },
              "reps": 10
            }
          ]
        }
      ]
    },
    {
      "id": "_bcyp2nms",
      "createdAt": "2019-11-11T21:23:48.685Z",
      "name": "Leg Curl Machine",
      "category": "Legs",
      "desc": "",
      "inputs": {
        "hasNotes": true,
        "hasDuration": false,
        "hasDistance": false,
        "hasWeight": true,
        "hasReps": true
      },
      "objectives": [
        { "type": "Notes", "text": "Notes" },
        { "type": "Breaks", "text": "1m" },
        { "type": "Tempo", "text": "Normal" },
        { "type": "Intensity", "text": "Medium" }
      ],
      "records": [
        {
          "createdAt": "2019-11-11T21:23:48.685Z",
          "sets": [
            {
              "duration": null,
              "distance": null,
              "weight": { "pounds": 90, "kilograms": 40.82 },
              "reps": 10
            },
            {
              "duration": null,
              "distance": null,
              "weight": { "pounds": 90, "kilograms": 40.82 },
              "reps": 10
            },
            {
              "duration": null,
              "distance": null,
              "weight": { "pounds": 90, "kilograms": 40.82 },
              "reps": 10
            }
          ]
        }
      ]
    },
    {
      "id": "_jv0xbr3y",
      "createdAt": "2019-11-11T21:23:48.685Z",
      "name": "Calf Extension Machine",
      "category": "Legs",
      "desc": "",
      "inputs": {
        "hasNotes": true,
        "hasDuration": false,
        "hasDistance": false,
        "hasWeight": true,
        "hasReps": true
      },
      "objectives": [
        { "type": "Notes", "text": "Notes" },
        { "type": "Breaks", "text": "1m" },
        { "type": "Tempo", "text": "Normal" },
        { "type": "Intensity", "text": "Medium" }
      ],
      "records": [
        {
          "createdAt": "2019-11-11T21:23:48.685Z",
          "sets": [
            {
              "duration": null,
              "distance": null,
              "weight": { "pounds": 175, "kilograms": 79.38 },
              "reps": 10
            },
            {
              "duration": null,
              "distance": null,
              "weight": { "pounds": 175, "kilograms": 79.38 },
              "reps": 10
            },
            {
              "duration": null,
              "distance": null,
              "weight": { "pounds": 175, "kilograms": 79.38 },
              "reps": 10
            }
          ]
        }
      ]
    },
    {
      "id": "_zolve4d1",
      "createdAt": "2019-11-11T21:23:48.685Z",
      "name": "Standing Glute Machine",
      "category": "Legs",
      "desc": "",
      "inputs": {
        "hasNotes": true,
        "hasDuration": false,
        "hasDistance": false,
        "hasWeight": true,
        "hasReps": true
      },
      "objectives": [
        { "type": "Notes", "text": "Notes" },
        { "type": "Breaks", "text": "1m" },
        { "type": "Tempo", "text": "Normal" },
        { "type": "Intensity", "text": "High" }
      ],
      "records": [
        {
          "createdAt": "2019-11-11T21:23:48.685Z",
          "sets": [
            {
              "duration": null,
              "distance": null,
              "weight": { "pounds": 125, "kilograms": 56.7 },
              "reps": 10
            },
            {
              "duration": null,
              "distance": null,
              "weight": { "pounds": 125, "kilograms": 56.7 },
              "reps": 10
            },
            {
              "duration": null,
              "distance": null,
              "weight": { "pounds": 125, "kilograms": 56.7 },
              "reps": 10
            }
          ]
        }
      ]
    },
    {
      "id": "_324k8nnt",
      "createdAt": "2019-11-11T21:23:48.685Z",
      "name": "Hip Abduction (Out) Machine",
      "category": "Legs",
      "desc": "",
      "inputs": {
        "hasNotes": true,
        "hasDuration": false,
        "hasDistance": false,
        "hasWeight": true,
        "hasReps": true
      },
      "objectives": [
        { "type": "Notes", "text": "Notes" },
        { "type": "Breaks", "text": "1m" },
        { "type": "Tempo", "text": "Normal" },
        { "type": "Intensity", "text": "Medium" }
      ],
      "records": [
        {
          "createdAt": "2019-11-11T21:23:48.685Z",
          "sets": [
            {
              "duration": null,
              "distance": null,
              "weight": { "pounds": 200, "kilograms": 90.72 },
              "reps": 10
            },
            {
              "duration": null,
              "distance": null,
              "weight": { "pounds": 200, "kilograms": 90.72 },
              "reps": 10
            },
            {
              "duration": null,
              "distance": null,
              "weight": { "pounds": 200, "kilograms": 90.72 },
              "reps": 10
            }
          ]
        }
      ]
    },
    {
      "id": "_0eauw2la",
      "createdAt": "2019-11-11T21:23:48.685Z",
      "name": "Hip Adduction (In) Machine",
      "category": "Legs",
      "desc": "",
      "inputs": {
        "hasNotes": true,
        "hasDuration": false,
        "hasDistance": false,
        "hasWeight": true,
        "hasReps": true
      },
      "objectives": [
        { "type": "Notes", "text": "Notes" },
        { "type": "Breaks", "text": "1m" },
        { "type": "Tempo", "text": "Normal" },
        { "type": "Intensity", "text": "Medium" }
      ],
      "records": [
        {
          "createdAt": "2019-11-11T21:23:48.685Z",
          "sets": [
            {
              "duration": null,
              "distance": null,
              "weight": { "pounds": 165, "kilograms": 74.84 },
              "reps": 10
            },
            {
              "duration": null,
              "distance": null,
              "weight": { "pounds": 165, "kilograms": 74.84 },
              "reps": 10
            },
            {
              "duration": null,
              "distance": null,
              "weight": { "pounds": 165, "kilograms": 74.84 },
              "reps": 10
            }
          ]
        }
      ]
    },
    {
      "id": "_c1swmvmf",
      "createdAt": "2019-11-11T21:23:48.685Z",
      "name": "Abdominal Crunch Machine",
      "category": "Core",
      "desc": "",
      "inputs": {
        "hasNotes": true,
        "hasDuration": false,
        "hasDistance": false,
        "hasWeight": true,
        "hasReps": true
      },
      "objectives": [
        { "type": "Notes", "text": "Notes" },
        { "type": "Breaks", "text": "2m" },
        { "type": "Tempo", "text": "Normal" },
        { "type": "Intensity", "text": "High" }
      ],
      "records": [
        {
          "createdAt": "2019-11-11T21:23:48.685Z",
          "sets": [
            {
              "duration": null,
              "distance": null,
              "weight": { "pounds": 35, "kilograms": 15.88 },
              "reps": 25
            },
            {
              "duration": null,
              "distance": null,
              "weight": { "pounds": 35, "kilograms": 15.88 },
              "reps": 25
            },
            {
              "duration": null,
              "distance": null,
              "weight": { "pounds": 35, "kilograms": 15.88 },
              "reps": 25
            },
            {
              "duration": null,
              "distance": null,
              "weight": { "pounds": 35, "kilograms": 15.88 },
              "reps": 25
            }
          ]
        }
      ]
    },
    {
      "id": "_8nm0oiqd",
      "createdAt": "2019-11-11T21:23:48.685Z",
      "name": "Oblique Side Bend",
      "category": "Core",
      "desc": "",
      "inputs": {
        "hasNotes": true,
        "hasDuration": false,
        "hasDistance": false,
        "hasWeight": true,
        "hasReps": true
      },
      "objectives": [
        { "type": "Notes", "text": "Notes" },
        { "type": "Breaks", "text": "1m" },
        { "type": "Tempo", "text": "Normal" },
        { "type": "Intensity", "text": "Medium" }
      ],
      "records": [
        {
          "createdAt": "2019-11-11T21:23:48.685Z",
          "sets": [
            {
              "duration": null,
              "distance": null,
              "weight": { "pounds": 45, "kilograms": 20.41 },
              "reps": 25
            },
            {
              "duration": null,
              "distance": null,
              "weight": { "pounds": 45, "kilograms": 20.41 },
              "reps": 25
            },
            {
              "duration": null,
              "distance": null,
              "weight": { "pounds": 45, "kilograms": 20.41 },
              "reps": 25
            },
            {
              "duration": null,
              "distance": null,
              "weight": { "pounds": 45, "kilograms": 20.41 },
              "reps": 25
            }
          ]
        }
      ]
    }
  ],
  "routines": [
    {
      "id": "_l69ioqwx",
      "createdAt": "2019-11-11T21:23:48.685Z",
      "name": "Chest and Triceps",
      "exerciseIds": [
        "_05pbj5ob",
        "_magkmc34",
        "_sk0hdyyh",
        "_20w6dhq8",
        "_wbimtk4s",
        "_7l0vnu8k",
        "_t6a1ipsj",
        "_dxs8ojvr"
      ]
    },
    {
      "id": "_ncwu4jvn",
      "createdAt": "2019-11-11T21:23:48.685Z",
      "name": "Back and Biceps",
      "exerciseIds": [
        "_05pbj5ob",
        "_p9nuiehd",
        "_kkrk4umz",
        "_1bkqyihd",
        "_nidp54eh",
        "_0ogbtvmk",
        "_749c818z",
        "_9gp3tgrp",
        "_dxs8ojvr"
      ]
    },
    {
      "id": "_iwj1n3e4",
      "createdAt": "2019-11-11T21:23:48.685Z",
      "name": "Legs, Shoulders, and Core",
      "exerciseIds": [
        "_05pbj5ob",
        "_v4xefkci",
        "_o2r0jlth",
        "_i9vgny5c",
        "_soelhkyp",
        "_h0ttfb8p",
        "_bcyp2nms",
        "_jv0xbr3y",
        "_zolve4d1",
        "_324k8nnt",
        "_0eauw2la",
        "_c1swmvmf",
        "_8nm0oiqd",
        "_dxs8ojvr"
      ]
    },
    {
      "id": "_v4r612sy",
      "createdAt": "2019-11-11T21:23:48.685Z",
      "name": "Chest Only",
      "exerciseIds": [
        "_05pbj5ob",
        "_magkmc34",
        "_sk0hdyyh",
        "_20w6dhq8",
        "_wbimtk4s",
        "_dxs8ojvr"
      ]
    },
    {
      "id": "_drxubgt2",
      "createdAt": "2019-11-11T21:23:48.685Z",
      "name": "Back Only",
      "exerciseIds": [
        "_05pbj5ob",
        "_p9nuiehd",
        "_kkrk4umz",
        "_1bkqyihd",
        "_nidp54eh",
        "_dxs8ojvr"
      ]
    },
    {
      "id": "_47f9z1up",
      "createdAt": "2019-11-11T21:23:48.685Z",
      "name": "Legs Only",
      "exerciseIds": [
        "_05pbj5ob",
        "_soelhkyp",
        "_h0ttfb8p",
        "_bcyp2nms",
        "_jv0xbr3y",
        "_zolve4d1",
        "_324k8nnt",
        "_0eauw2la",
        "_dxs8ojvr"
      ]
    },
    {
      "id": "_4keksdaj",
      "createdAt": "2019-11-11T21:23:48.685Z",
      "name": "Arms and Core",
      "exerciseIds": [
        "_05pbj5ob",
        "_v4xefkci",
        "_o2r0jlth",
        "_i9vgny5c",
        "_0ogbtvmk",
        "_7l0vnu8k",
        "_749c818z",
        "_t6a1ipsj",
        "_9gp3tgrp",
        "_c1swmvmf",
        "_8nm0oiqd",
        "_dxs8ojvr"
      ]
    },
    {
      "id": "_5ndtpkip",
      "createdAt": "2019-11-11T21:23:48.685Z",
      "name": "General Cardio",
      "exerciseIds": ["_kplyey7i", "_dxs8ojvr"]
    }
  ]
}
